ebx_printbox/__init__.py
ebx_printbox-1.0.2.dist-info/LICENSE
ebx_printbox-1.0.2.dist-info/METADATA
ebx_printbox-1.0.2.dist-info/WHEEL
ebx_printbox-1.0.2.dist-info/top_level.txt
ebx_printbox-1.0.2.dist-info/RECORD
