Metadata-Version: 2.1
Name: ebx-printbox
Version: 1.0.2
Summary: functions to delimit a box on screen (With a border or not) and print strictly inside the created box, with scroll to the new lines.
Home-page: https://github.com/faustobranco/ebx_printbox
Author: Fausto Branco
Author-email: fausto.branco@gmail.com
License: UNKNOWN
Project-URL: Bug Tracker, https://github.com/faustobranco/ebx_printbox/issues
Platform: UNKNOWN
Classifier: Programming Language :: Python :: 3
Classifier: License :: OSI Approved :: MIT License
Classifier: Operating System :: OS Independent
Requires-Python: >=3.6
